PyPhoenixS-1.0.dist-info/DESCRIPTION.rst
PyPhoenixS-1.0.dist-info/METADATA
PyPhoenixS-1.0.dist-info/RECORD
PyPhoenixS-1.0.dist-info/WHEEL
PyPhoenixS-1.0.dist-info/entry_points.txt
PyPhoenixS-1.0.dist-info/metadata.json
PyPhoenixS-1.0.dist-info/top_level.txt
pyphoenix/__init__.py
pyphoenix/exc.py
pyphoenix/phoenix.py
pyphoenix/sqlalchemy_phoenix.py
